ci/.include/logo.png
ci/.include/theme.css
ci/api/account.py
ci/api/endpoint.py
ci/api/module/__init__.py
ci/api/module/hercules.py
ci/api/module/loki.py
ci/app/__init__.py
ci/app/index.py
ci/app/node/__init__.py
ci/app/node/account/__init__.py
ci/app/node/account/_temp.py
ci/app/node/account/delete.py
ci/app/node/account/login.py
ci/app/node/account/logout.py
ci/app/node/account/recover.py
ci/app/node/account/refresh.py
ci/app/node/account/register.py
ci/app/node/dev/pipelines.py
ci/app/node/pipelines.py
ci/app/node/settings.py
ci/app/node/test.py
ci/cli.py
ci/cloud/module/__init__.py
ci/core.py
ci/loc/daemon/minerva.py
ci/loc/plugin/external.py
ci/loc/plugin/internal.py
ci/utility/__init__.py
ci/utility/cryptographic.py
ci/utility/generic.py
ci/utility/streamlit.py
ci/utility/terminal.py
ci/utility/validation.py
ci/var.py
cephalon_interface-0.1.6.dist-info/LICENSE
cephalon_interface-0.1.6.dist-info/METADATA
cephalon_interface-0.1.6.dist-info/WHEEL
cephalon_interface-0.1.6.dist-info/entry_points.txt
cephalon_interface-0.1.6.dist-info/RECORD
